MANIFEST.in
README.rst
setup.py
django_mobile_redirect.egg-info/PKG-INFO
django_mobile_redirect.egg-info/SOURCES.txt
django_mobile_redirect.egg-info/dependency_links.txt
django_mobile_redirect.egg-info/not-zip-safe
django_mobile_redirect.egg-info/requires.txt
django_mobile_redirect.egg-info/top_level.txt
mobile_redirect/__init__.py
mobile_redirect/middleware.py
mobile_redirect/models.py
mobile_redirect/tests/__init__.py
mobile_redirect/tests/urls.py