Metadata-Version: 1.0
Name: django-mobile-redirect
Version: 1.0.0
Summary: Redirects devices with mobile user agent strings to a specified url.
Home-page: https://github.com/ryanbagwell/django-mobile-redirect
Author: Ryan Bagwell
Author-email: ryan@ryanbagwell.com
License: MIT
Platform: UNKNOWN
